<?xml version="1.0" encoding="utf-8"?>
<library xmlns="duell">

    <supported-duell-tool version="4.0.0+" />

    <duelllib name="runloop" version="2.0.0+" />
    <duelllib name="polygonal-ds" version="2.0.0+" />
    <duelllib name="logger" version="1.0.0+" />
    <duelllib name="hxjni" version="1.0.0+" if="android"/>

    <haxelib name="msignal" version="1.2.2" />
    <haxelib name="hamcrest" version="https://github.com/gameduell/hamcrest-haxe.git patch-1 src" />

    <platform-config>
    	<android>
    		<java-source name="TestHTTPLoggerPoster" path="java" />
    		<permission name="android.permission.INTERNET" />
		</android>

        <documentation>
            <documentation-folder library="unittest" path="documentation" />
        </documentation>

	</platform-config>
</library>
